as-mongodb/__init__.py
as-mongodb/config_utils.py
as-mongodb/datetime_utils.py
as-mongodb/db_utils.py
as-mongodb/errors.py
as-mongodb/stream_utils.py
as-mongodb/sync_strategies/change_streams.py
as-mongodb/sync_strategies/common.py
as-mongodb/sync_strategies/full_table.py
as-mongodb/sync_strategies/incremental.py
as_mongodb/__init__.py
as_mongodb/config_utils.py
as_mongodb/datetime_utils.py
as_mongodb/db_utils.py
as_mongodb/errors.py
as_mongodb/stream_utils.py
as_mongodb/sync_strategies/change_streams.py
as_mongodb/sync_strategies/common.py
as_mongodb/sync_strategies/full_table.py
as_mongodb/sync_strategies/incremental.py
as_mongodb-1.4.1.dist-info/LICENSE
as_mongodb-1.4.1.dist-info/METADATA
as_mongodb-1.4.1.dist-info/WHEEL
as_mongodb-1.4.1.dist-info/entry_points.txt
as_mongodb-1.4.1.dist-info/top_level.txt
as_mongodb-1.4.1.dist-info/RECORD
